{
  "2026-04-10": {
    "Palmerstown": {
      "store": "Palmerstown",
      "code": "356",
      "report": "top cash margin lines",
      "scraped_at": "2026-04-10T10:15:11.540105+01:00",
      "date": "2026-04-10",
      "data": {
        "headers": [
          "Merchandising Structure - Article SV TB",
          "Week 14 2026",
          "Week 14 2026",
          "Week 14 2026",
          "Week 14 2026"
        ],
        "rows": [
          {
            "Merchandising Structure - Article SV TB": {
              "v": "Merchandising Structure - Article SV TB",
              "t": "str"
            },
            "Week 14 2026": {
              "v": "Retail Scan Margin %",
              "t": "str"
            }
          },
          {
            "Merchandising Structure - Article SV TB": {
              "v": "1123802 000 CHICKEN FILLET ROLL LARGE | 1PCE 0251100000000",
              "t": "str"
            },
            "Week 14 2026": {
              "v": 54.7057,
              "t": "pct"
            }
          },
          {
            "Merchandising Structure - Article SV TB": {
              "v": "1150694 000 SV CHICKEN FILLETS 5FOR€6|125GRM 0290870000000",
              "t": "str"
            },
            "Week 14 2026": {
              "v": 19.3591,
              "t": "pct"
            }
          },
          {
            "Merchandising Structure - Article SV TB": {
              "v": "1386984 000 KEELINGS FAMILY PK STRAWBERRIES | 300GRM 53994356",
              "t": "str"
            },
            "Week 14 2026": {
              "v": 12.5332,
              "t": "pct"
            }
          },
          {
            "Merchandising Structure - Article SV TB": {
              "v": "1653589 000 PBOB CHICKEN SKEWERS | 1PCE 0249800000000",
              "t": "str"
            },
            "Week 14 2026": {
              "v": 24.374,
              "t": "pct"
            }
          },
          {
            "Merchandising Structure - Article SV TB": {
              "v": "1025220 000 SUPERVALU BAG FOR LIFE RECYCLED| 1PCE 5099839694455",
              "t": "str"
            },
            "Week 14 2026": {
              "v": 54.9994,
              "t": "pct"
            }
          },
          {
            "Merchandising Structure - Article SV TB": {
              "v": "1600350 000 SV FREE RANGE LARGE EGGS| 12PCE 5099839581724",
              "t": "str"
            },
            "Week 14 2026": {
              "v": 20.9995,
              "t": "pct"
            }
          },
          {
            "Merchandising Structure - Article SV TB": {
              "v": "1683185 003 SIGNATURE TASTES BLUEBERRY | 200GRM 5099839732867",
              "t": "str"
            },
            "Week 14 2026": {
              "v": 16.014,
              "t": "pct"
            }
          },
          {
            "Merchandising Structure - Article SV TB": {
              "v": "1040784 000 SAUSAGE ROLLS MULTI-BUY| 1PCE 0237890000000",
              "t": "str"
            },
            "Week 14 2026": {
              "v": 57.4375,
              "t": "pct"
            }
          },
          {
            "Merchandising Structure - Article SV TB": {
              "v": "1349780 001 SUPERQUINN PORK SAUSAGES| 480GRM 5099839584312",
              "t": "str"
            },
            "Week 14 2026": {
              "v": 28.5227,
              "t": "pct"
            }
          },
          {
            "Merchandising Structure - Article SV TB": {
              "v": "1148321 000 WASHED ROOSTER | 2.5KGM 5390563001572",
              "t": "str"
            },
            "Week 14 2026": {
              "v": 33.1849,
              "t": "pct"
            }
          },
          {
            "Merchandising Structure - Article SV TB": {
              "v": "1183884 001 AVONMORE LOW FAT SUPER MILK|1.75LTR 5011056021845",
              "t": "str"
            },
            "Week 14 2026": {
              "v": 24.7458,
              "t": "pct"
            }
          },
          {
            "Merchandising Structure - Article SV TB": {
              "v": "1035239 000 MEDIUM FRESH SALAD| 1PCE 61003",
              "t": "str"
            },
            "Week 14 2026": {
              "v": 42.8351,
              "t": "pct"
            }
          },
          {
            "Merchandising Structure - Article SV TB": {
              "v": "1858672 000 DEMI BAGUETTE| 130GRM 5099839724473",
              "t": "str"
            },
            "Week 14 2026": {
              "v": 67.1253,
              "t": "pct"
            }
          },
          {
            "Merchandising Structure - Article SV TB": {
              "v": "1018392 000 A/MORE LOW FAT SUPERMILK [T T]| 1LTR 5011056020428",
              "t": "str"
            },
            "Week 14 2026": {
              "v": 24.0,
              "t": "pct"
            }
          },
          {
            "Merchandising Structure - Article SV TB": {
              "v": "1013680 000 SV BANANAS  LOOSE NORMAL |1KGM 0287810000000",
              "t": "str"
            },
            "Week 14 2026": {
              "v": 11.5708,
              "t": "pct"
            }
          },
          {
            "Merchandising Structure - Article SV TB": {
              "v": "1183884 000 AVONMORE WHOLE SUPER MILK|1.75LTR 5011056021852",
              "t": "str"
            },
            "Week 14 2026": {
              "v": 24.7458,
              "t": "pct"
            }
          },
          {
            "Merchandising Structure - Article SV TB": {
              "v": "1018502 000 BRENNANS WHITE SLICED PAN PP .| 800GRM 5011059000014",
              "t": "str"
            },
            "Week 14 2026": {
              "v": 13.8756,
              "t": "pct"
            }
          },
          {
            "Merchandising Structure - Article SV TB": {
              "v": "1009043 000 SUPERVALU FRESH MILK| 3LTR 5099839260230",
              "t": "str"
            },
            "Week 14 2026": {
              "v": 15.4615,
              "t": "pct"
            }
          },
          {
            "Merchandising Structure - Article SV TB": {
              "v": "1016164 000 BRENNANS WHITE HALF PAN | 390GRM 5011059001158",
              "t": "str"
            },
            "Week 14 2026": {
              "v": 32.0,
              "t": "pct"
            }
          },
          {
            "Merchandising Structure - Article SV TB": {
              "v": "1118422 000 NOVELTY CAKE| 1PCE 0248200000000",
              "t": "str"
            },
            "Week 14 2026": {
              "v": 43.25,
              "t": "pct"
            }
          },
          {
            "Merchandising Structure - Article SV TB": {
              "v": "1310257 001 ALL BUTTER CROISSANT | 70GRM 7005",
              "t": "str"
            },
            "Week 14 2026": {
              "v": 47.3129,
              "t": "pct"
            }
          },
          {
            "Merchandising Structure - Article SV TB": {
              "v": "1000941 000 SUPERVALU IRISH CREAMERY BUTTER | 454GRM 5099839244650",
              "t": "str"
            },
            "Week 14 2026": {
              "v": 7.5013,
              "t": "pct"
            }
          },
          {
            "Merchandising Structure - Article SV TB": {
              "v": "1026343 000 SV FREE RANGE LARGE EGGS| 6PCE 5099839044380",
              "t": "str"
            },
            "Week 14 2026": {
              "v": 12.9971,
              "t": "pct"
            }
          },
          {
            "Merchandising Structure - Article SV TB": {
              "v": "1018390 000 AVONMORE MILK CARTON| 1LTR 5011056020350",
              "t": "str"
            },
            "Week 14 2026": {
              "v": 19.4969,
              "t": "pct"
            }
          },
          {
            "Merchandising Structure - Article SV TB": {
              "v": "1025460 000 SUPERVALU FRESH MILK| 2LTR 5099839041358",
              "t": "str"
            },
            "Week 14 2026": {
              "v": 8.4444,
              "t": "pct"
            }
          },
          {
            "Merchandising Structure - Article SV TB": {
              "v": "1008857 001 SV PINK LADY TRAY| 6PCE 5099839575327",
              "t": "str"
            },
            "Week 14 2026": {
              "v": 13.4839,
              "t": "pct"
            }
          },
          {
            "Merchandising Structure - Article SV TB": {
              "v": "1016345 000 SIG TASTES RASPBERRY| 125GRM 5099839255410",
              "t": "str"
            },
            "Week 14 2026": {
              "v": 17.9931,
              "t": "pct"
            }
          },
          {
            "Merchandising Structure - Article SV TB": {
              "v": "1020045 000 BREAKFAST SAUSAGES| 1PCE 0286870000000",
              "t": "str"
            },
            "Week 14 2026": {
              "v": 65.3526,
              "t": "pct"
            }
          },
          {
            "Merchandising Structure - Article SV TB": {
              "v": "1005787 000 AVONMORE FRESH MILK| 2LTR 5011056020053",
              "t": "str"
            },
            "Week 14 2026": {
              "v": 14.4981,
              "t": "pct"
            }
          },
          {
            "Merchandising Structure - Article SV TB": {
              "v": "1019540 000 SUPERVALU CUCUMBER [IRISH] | 1PCE 5099839311444",
              "t": "str"
            },
            "Week 14 2026": {
              "v": 23.0337,
              "t": "pct"
            }
          },
          {
            "Merchandising Structure - Article SV TB": {
              "v": "1025461 000 SUPERVALU LIGHT MILK | 2LTR 5099839041365",
              "t": "str"
            },
            "Week 14 2026": {
              "v": 8.4444,
              "t": "pct"
            }
          },
          {
            "Merchandising Structure - Article SV TB": {
              "v": "1040062 000 SUPERVALU FRESH MILK | 1LTR 5099839287916",
              "t": "str"
            },
            "Week 14 2026": {
              "v": 14.6957,
              "t": "pct"
            }
          },
          {
            "Merchandising Structure - Article SV TB": {
              "v": "1022674 001 SUPERVALU CARROT BAG [IRISH] | 1KGM 5099839280665",
              "t": "str"
            },
            "Week 14 2026": {
              "v": 13.4975,
              "t": "pct"
            }
          },
          {
            "Merchandising Structure - Article SV TB": {
              "v": "1021128 002 SIGNATURE TASTES CLEMENGOLD LOOSE| 1PCE 81983",
              "t": "str"
            },
            "Week 14 2026": {
              "v": 22.0044,
              "t": "pct"
            }
          },
          {
            "Merchandising Structure - Article SV TB": {
              "v": "1018071 000 SV RED GRAPE SEEDLESS PNT | 500GRM 5099839095078",
              "t": "str"
            },
            "Week 14 2026": {
              "v": 10.9133,
              "t": "pct"
            }
          },
          {
            "Merchandising Structure - Article SV TB": {
              "v": "1045844 000 SUPERVALU LIGHT MILK| 1LTR 5099839306396",
              "t": "str"
            },
            "Week 14 2026": {
              "v": 14.6957,
              "t": "pct"
            }
          },
          {
            "Merchandising Structure - Article SV TB": {
              "v": "1026694 000 SUPERVALU SCALLIONS BUNCH | 1PCE 88227",
              "t": "str"
            },
            "Week 14 2026": {
              "v": 15.7303,
              "t": "pct"
            }
          },
          {
            "Merchandising Structure - Article SV TB": {
              "v": "1176123 001 FIREBLOC FIRELOG 920G | 1PCE 8712483220180",
              "t": "str"
            },
            "Week 14 2026": {
              "v": 9.0635,
              "t": "pct"
            }
          },
          {
            "Merchandising Structure - Article SV TB": {
              "v": "1042892 005 PETIT PAIN LARGE | 74GRM 81302",
              "t": "str"
            },
            "Week 14 2026": {
              "v": 60.9538,
              "t": "pct"
            }
          },
          {
            "Merchandising Structure - Article SV TB": {
              "v": "1025921 000 SV CLOSED CUP MUSHROOMS| 250GRM 5099839045547",
              "t": "str"
            },
            "Week 14 2026": {
              "v": 13.0051,
              "t": "pct"
            }
          },
          {
            "Merchandising Structure - Article SV TB": {
              "v": "1021584 000 SUPERVALU PEARS LOOSE| 1PCE 4891",
              "t": "str"
            },
            "Week 14 2026": {
              "v": 22.0145,
              "t": "pct"
            }
          },
          {
            "Merchandising Structure - Article SV TB": {
              "v": "1018820 000 SV ORANGES LOOSE LARGE | 1PCE 5099839642845",
              "t": "str"
            },
            "Week 14 2026": {
              "v": 17.9873,
              "t": "pct"
            }
          },
          {
            "Merchandising Structure - Article SV TB": {
              "v": "1042883 001 WHITE BATCH CRUSTY ROLL| 90GRM 81300",
              "t": "str"
            },
            "Week 14 2026": {
              "v": 54.5965,
              "t": "pct"
            }
          },
          {
            "Merchandising Structure - Article SV TB": {
              "v": "1134669 000 SUPERVALU RED PEPPERS| 1PCE 45822",
              "t": "str"
            },
            "Week 14 2026": {
              "v": 24.3119,
              "t": "pct"
            }
          }
        ]
      }
    },
    "Balbriggan": {
      "store": "Balbriggan",
      "code": "374",
      "report": "top cash margin lines",
      "scraped_at": "2026-04-10T10:15:11.540105+01:00",
      "date": "2026-04-10",
      "data": {
        "headers": [],
        "rows": []
      },
      "error": "Export file never appeared."
    },
    "Skerries": {
      "store": "Skerries",
      "code": "424",
      "report": "top cash margin lines",
      "scraped_at": "2026-04-10T10:15:11.540105+01:00",
      "date": "2026-04-10",
      "data": {
        "headers": [
          "Merchandising Structure - Article SV TB",
          "Week 14 2026",
          "Week 14 2026",
          "Week 14 2026",
          "Week 14 2026"
        ],
        "rows": [
          {
            "Merchandising Structure - Article SV TB": {
              "v": "Merchandising Structure - Article SV TB",
              "t": "str"
            },
            "Week 14 2026": {
              "v": "Retail Scan Margin %",
              "t": "str"
            }
          },
          {
            "Merchandising Structure - Article SV TB": {
              "v": "1123802 000 CHICKEN FILLET ROLL LARGE | 1PCE 0251100000000",
              "t": "str"
            },
            "Week 14 2026": {
              "v": 54.7057,
              "t": "pct"
            }
          },
          {
            "Merchandising Structure - Article SV TB": {
              "v": "1150694 000 SV CHICKEN FILLETS 5FOR€6|125GRM 0290870000000",
              "t": "str"
            },
            "Week 14 2026": {
              "v": 19.3591,
              "t": "pct"
            }
          },
          {
            "Merchandising Structure - Article SV TB": {
              "v": "1386984 000 KEELINGS FAMILY PK STRAWBERRIES | 300GRM 53994356",
              "t": "str"
            },
            "Week 14 2026": {
              "v": 12.5332,
              "t": "pct"
            }
          },
          {
            "Merchandising Structure - Article SV TB": {
              "v": "1653589 000 PBOB CHICKEN SKEWERS | 1PCE 0249800000000",
              "t": "str"
            },
            "Week 14 2026": {
              "v": 24.374,
              "t": "pct"
            }
          },
          {
            "Merchandising Structure - Article SV TB": {
              "v": "1025220 000 SUPERVALU BAG FOR LIFE RECYCLED| 1PCE 5099839694455",
              "t": "str"
            },
            "Week 14 2026": {
              "v": 54.9994,
              "t": "pct"
            }
          },
          {
            "Merchandising Structure - Article SV TB": {
              "v": "1600350 000 SV FREE RANGE LARGE EGGS| 12PCE 5099839581724",
              "t": "str"
            },
            "Week 14 2026": {
              "v": 20.9995,
              "t": "pct"
            }
          },
          {
            "Merchandising Structure - Article SV TB": {
              "v": "1683185 003 SIGNATURE TASTES BLUEBERRY | 200GRM 5099839732867",
              "t": "str"
            },
            "Week 14 2026": {
              "v": 16.014,
              "t": "pct"
            }
          },
          {
            "Merchandising Structure - Article SV TB": {
              "v": "1040784 000 SAUSAGE ROLLS MULTI-BUY| 1PCE 0237890000000",
              "t": "str"
            },
            "Week 14 2026": {
              "v": 57.4375,
              "t": "pct"
            }
          },
          {
            "Merchandising Structure - Article SV TB": {
              "v": "1349780 001 SUPERQUINN PORK SAUSAGES| 480GRM 5099839584312",
              "t": "str"
            },
            "Week 14 2026": {
              "v": 28.5227,
              "t": "pct"
            }
          },
          {
            "Merchandising Structure - Article SV TB": {
              "v": "1148321 000 WASHED ROOSTER | 2.5KGM 5390563001572",
              "t": "str"
            },
            "Week 14 2026": {
              "v": 33.1849,
              "t": "pct"
            }
          },
          {
            "Merchandising Structure - Article SV TB": {
              "v": "1183884 001 AVONMORE LOW FAT SUPER MILK|1.75LTR 5011056021845",
              "t": "str"
            },
            "Week 14 2026": {
              "v": 24.7458,
              "t": "pct"
            }
          },
          {
            "Merchandising Structure - Article SV TB": {
              "v": "1035239 000 MEDIUM FRESH SALAD| 1PCE 61003",
              "t": "str"
            },
            "Week 14 2026": {
              "v": 42.8351,
              "t": "pct"
            }
          },
          {
            "Merchandising Structure - Article SV TB": {
              "v": "1858672 000 DEMI BAGUETTE| 130GRM 5099839724473",
              "t": "str"
            },
            "Week 14 2026": {
              "v": 67.1253,
              "t": "pct"
            }
          },
          {
            "Merchandising Structure - Article SV TB": {
              "v": "1018392 000 A/MORE LOW FAT SUPERMILK [T T]| 1LTR 5011056020428",
              "t": "str"
            },
            "Week 14 2026": {
              "v": 24.0,
              "t": "pct"
            }
          },
          {
            "Merchandising Structure - Article SV TB": {
              "v": "1013680 000 SV BANANAS  LOOSE NORMAL |1KGM 0287810000000",
              "t": "str"
            },
            "Week 14 2026": {
              "v": 11.5708,
              "t": "pct"
            }
          },
          {
            "Merchandising Structure - Article SV TB": {
              "v": "1183884 000 AVONMORE WHOLE SUPER MILK|1.75LTR 5011056021852",
              "t": "str"
            },
            "Week 14 2026": {
              "v": 24.7458,
              "t": "pct"
            }
          },
          {
            "Merchandising Structure - Article SV TB": {
              "v": "1018502 000 BRENNANS WHITE SLICED PAN PP .| 800GRM 5011059000014",
              "t": "str"
            },
            "Week 14 2026": {
              "v": 13.8756,
              "t": "pct"
            }
          },
          {
            "Merchandising Structure - Article SV TB": {
              "v": "1009043 000 SUPERVALU FRESH MILK| 3LTR 5099839260230",
              "t": "str"
            },
            "Week 14 2026": {
              "v": 15.4615,
              "t": "pct"
            }
          },
          {
            "Merchandising Structure - Article SV TB": {
              "v": "1016164 000 BRENNANS WHITE HALF PAN | 390GRM 5011059001158",
              "t": "str"
            },
            "Week 14 2026": {
              "v": 32.0,
              "t": "pct"
            }
          },
          {
            "Merchandising Structure - Article SV TB": {
              "v": "1118422 000 NOVELTY CAKE| 1PCE 0248200000000",
              "t": "str"
            },
            "Week 14 2026": {
              "v": 43.25,
              "t": "pct"
            }
          },
          {
            "Merchandising Structure - Article SV TB": {
              "v": "1310257 001 ALL BUTTER CROISSANT | 70GRM 7005",
              "t": "str"
            },
            "Week 14 2026": {
              "v": 47.3129,
              "t": "pct"
            }
          },
          {
            "Merchandising Structure - Article SV TB": {
              "v": "1000941 000 SUPERVALU IRISH CREAMERY BUTTER | 454GRM 5099839244650",
              "t": "str"
            },
            "Week 14 2026": {
              "v": 7.5013,
              "t": "pct"
            }
          },
          {
            "Merchandising Structure - Article SV TB": {
              "v": "1026343 000 SV FREE RANGE LARGE EGGS| 6PCE 5099839044380",
              "t": "str"
            },
            "Week 14 2026": {
              "v": 12.9971,
              "t": "pct"
            }
          },
          {
            "Merchandising Structure - Article SV TB": {
              "v": "1018390 000 AVONMORE MILK CARTON| 1LTR 5011056020350",
              "t": "str"
            },
            "Week 14 2026": {
              "v": 19.4969,
              "t": "pct"
            }
          },
          {
            "Merchandising Structure - Article SV TB": {
              "v": "1025460 000 SUPERVALU FRESH MILK| 2LTR 5099839041358",
              "t": "str"
            },
            "Week 14 2026": {
              "v": 8.4444,
              "t": "pct"
            }
          },
          {
            "Merchandising Structure - Article SV TB": {
              "v": "1008857 001 SV PINK LADY TRAY| 6PCE 5099839575327",
              "t": "str"
            },
            "Week 14 2026": {
              "v": 13.4839,
              "t": "pct"
            }
          },
          {
            "Merchandising Structure - Article SV TB": {
              "v": "1016345 000 SIG TASTES RASPBERRY| 125GRM 5099839255410",
              "t": "str"
            },
            "Week 14 2026": {
              "v": 17.9931,
              "t": "pct"
            }
          },
          {
            "Merchandising Structure - Article SV TB": {
              "v": "1020045 000 BREAKFAST SAUSAGES| 1PCE 0286870000000",
              "t": "str"
            },
            "Week 14 2026": {
              "v": 65.3526,
              "t": "pct"
            }
          },
          {
            "Merchandising Structure - Article SV TB": {
              "v": "1005787 000 AVONMORE FRESH MILK| 2LTR 5011056020053",
              "t": "str"
            },
            "Week 14 2026": {
              "v": 14.4981,
              "t": "pct"
            }
          },
          {
            "Merchandising Structure - Article SV TB": {
              "v": "1019540 000 SUPERVALU CUCUMBER [IRISH] | 1PCE 5099839311444",
              "t": "str"
            },
            "Week 14 2026": {
              "v": 23.0337,
              "t": "pct"
            }
          },
          {
            "Merchandising Structure - Article SV TB": {
              "v": "1025461 000 SUPERVALU LIGHT MILK | 2LTR 5099839041365",
              "t": "str"
            },
            "Week 14 2026": {
              "v": 8.4444,
              "t": "pct"
            }
          },
          {
            "Merchandising Structure - Article SV TB": {
              "v": "1040062 000 SUPERVALU FRESH MILK | 1LTR 5099839287916",
              "t": "str"
            },
            "Week 14 2026": {
              "v": 14.6957,
              "t": "pct"
            }
          },
          {
            "Merchandising Structure - Article SV TB": {
              "v": "1022674 001 SUPERVALU CARROT BAG [IRISH] | 1KGM 5099839280665",
              "t": "str"
            },
            "Week 14 2026": {
              "v": 13.4975,
              "t": "pct"
            }
          },
          {
            "Merchandising Structure - Article SV TB": {
              "v": "1021128 002 SIGNATURE TASTES CLEMENGOLD LOOSE| 1PCE 81983",
              "t": "str"
            },
            "Week 14 2026": {
              "v": 22.0044,
              "t": "pct"
            }
          },
          {
            "Merchandising Structure - Article SV TB": {
              "v": "1018071 000 SV RED GRAPE SEEDLESS PNT | 500GRM 5099839095078",
              "t": "str"
            },
            "Week 14 2026": {
              "v": 10.9133,
              "t": "pct"
            }
          },
          {
            "Merchandising Structure - Article SV TB": {
              "v": "1045844 000 SUPERVALU LIGHT MILK| 1LTR 5099839306396",
              "t": "str"
            },
            "Week 14 2026": {
              "v": 14.6957,
              "t": "pct"
            }
          },
          {
            "Merchandising Structure - Article SV TB": {
              "v": "1026694 000 SUPERVALU SCALLIONS BUNCH | 1PCE 88227",
              "t": "str"
            },
            "Week 14 2026": {
              "v": 15.7303,
              "t": "pct"
            }
          },
          {
            "Merchandising Structure - Article SV TB": {
              "v": "1176123 001 FIREBLOC FIRELOG 920G | 1PCE 8712483220180",
              "t": "str"
            },
            "Week 14 2026": {
              "v": 9.0635,
              "t": "pct"
            }
          },
          {
            "Merchandising Structure - Article SV TB": {
              "v": "1042892 005 PETIT PAIN LARGE | 74GRM 81302",
              "t": "str"
            },
            "Week 14 2026": {
              "v": 60.9538,
              "t": "pct"
            }
          },
          {
            "Merchandising Structure - Article SV TB": {
              "v": "1025921 000 SV CLOSED CUP MUSHROOMS| 250GRM 5099839045547",
              "t": "str"
            },
            "Week 14 2026": {
              "v": 13.0051,
              "t": "pct"
            }
          },
          {
            "Merchandising Structure - Article SV TB": {
              "v": "1021584 000 SUPERVALU PEARS LOOSE| 1PCE 4891",
              "t": "str"
            },
            "Week 14 2026": {
              "v": 22.0145,
              "t": "pct"
            }
          },
          {
            "Merchandising Structure - Article SV TB": {
              "v": "1018820 000 SV ORANGES LOOSE LARGE | 1PCE 5099839642845",
              "t": "str"
            },
            "Week 14 2026": {
              "v": 17.9873,
              "t": "pct"
            }
          },
          {
            "Merchandising Structure - Article SV TB": {
              "v": "1042883 001 WHITE BATCH CRUSTY ROLL| 90GRM 81300",
              "t": "str"
            },
            "Week 14 2026": {
              "v": 54.5965,
              "t": "pct"
            }
          },
          {
            "Merchandising Structure - Article SV TB": {
              "v": "1134669 000 SUPERVALU RED PEPPERS| 1PCE 45822",
              "t": "str"
            },
            "Week 14 2026": {
              "v": 24.3119,
              "t": "pct"
            }
          }
        ]
      }
    }
  }
}